ez_django_common/__init__.py
ez_django_common/apps.py
ez_django_common/custom_throttle.py
ez_django_common/middleware.py
ez_django_common/mixins.py
ez_django_common/models.py
ez_django_common/permissions.py
ez_django_common/responses.py
ez_django_common/storages.py
ez_django_common/watchlog.py
ez_django_common/admin/__init__.py
ez_django_common/admin/admin.py
ez_django_common/admin/inlines.py
ez_django_common/custom_responses/__init__.py
ez_django_common/custom_responses/enveloper.py
ez_django_common/custom_responses/exception.py
ez_django_common/custom_responses/jwt.py
ez_django_common/custom_responses/mixins.py
ez_django_common/custom_responses/pagination.py
ez_django_common/custom_responses/response.py
ez_django_common/custom_responses/viewsets.py
ez_django_common/locale/fa/LC_MESSAGES/django.mo
ez_django_common/locale/fa/LC_MESSAGES/django.po
ez_django_common/migrations/__init__.py
ez_django_common/static/fonts/IRANYekanWebRegular.ttf
ez_django_common/templates/admin/base.html
ez_django_common/utils/__init__.py
ez_django_common/utils/caching_utils.py
ez_django_common/utils/loggers.py
ez_django_common/utils/sms.py
ez_django_common/utils/utils.py
ez_django_common/utils/webp_utils.py
ez_django_common-1.6.2.dist-info/licenses/LICENSE
ez_django_common-1.6.2.dist-info/METADATA
ez_django_common-1.6.2.dist-info/WHEEL
ez_django_common-1.6.2.dist-info/top_level.txt
ez_django_common-1.6.2.dist-info/RECORD
