Metadata-Version: 2.4
Name: ez-django-common
Version: 1.6.2
Summary: EZDjangoCommon
Home-page: https://github.com/ezhoosh/EZDjangoCommon
Download-URL: https://pypi.python.org/pypi/ez-django-common/
Author: ezhoosh
Author-email: ezhoosh@ezhoosh.com
License: MIT
Keywords: common
Platform: any
Classifier: Environment :: Web Environment
Classifier: Intended Audience :: Developers
Classifier: Operating System :: OS Independent
Classifier: Topic :: Software Development :: Libraries :: Application Frameworks
Classifier: Topic :: Software Development :: Libraries :: Python Modules
Classifier: Programming Language :: Python
Classifier: Programming Language :: Python :: 3.8
Classifier: Programming Language :: Python :: 3.9
Classifier: Programming Language :: Python :: 3.10
Classifier: Programming Language :: Python :: 3.11
Classifier: Framework :: Django
Classifier: Framework :: Django :: 2.2
Classifier: Framework :: Django :: 3.2
Classifier: Framework :: Django :: 4.2
Classifier: Framework :: Django :: 5.0
Requires-Python: >=3
License-File: LICENSE
Requires-Dist: django
Requires-Dist: django-unfold
Requires-Dist: django-tinymce
Requires-Dist: django-lifecycle
Requires-Dist: djangorestframework
Requires-Dist: django-jalali
Requires-Dist: googletrans==4.0.0rc1
Requires-Dist: django-modeltranslation
Requires-Dist: loguru
Requires-Dist: kavenegar
Requires-Dist: drf-spectacular
Requires-Dist: django-media-uploader-widget
Requires-Dist: django-image-uploader-widget
Requires-Dist: django-storages
Requires-Dist: boto3
Requires-Dist: django-webpfield
Provides-Extra: watchlog
Requires-Dist: opentelemetry-api; extra == "watchlog"
Requires-Dist: opentelemetry-sdk; extra == "watchlog"
Requires-Dist: opentelemetry-exporter-otlp; extra == "watchlog"
Requires-Dist: opentelemetry-instrumentation; extra == "watchlog"
Requires-Dist: opentelemetry-instrumentation-django; extra == "watchlog"
Dynamic: author
Dynamic: author-email
Dynamic: classifier
Dynamic: description
Dynamic: description-content-type
Dynamic: download-url
Dynamic: home-page
Dynamic: keywords
Dynamic: license
Dynamic: license-file
Dynamic: platform
Dynamic: provides-extra
Dynamic: requires-dist
Dynamic: requires-python
Dynamic: summary
